fl_manager/utils/job_generator/__init__.py
fl_manager/utils/job_generator/job_creator.py
fl_manager/utils/job_generator/py.typed
fl_manager/utils/job_generator/federated_job/__init__.py
fl_manager/utils/job_generator/federated_job/federated_job.py
fl_manager/utils/job_generator/federated_job/federated_job_factory.py
fl_manager/utils/job_generator/federated_job/pt/__init__.py
fl_manager/utils/job_generator/federated_job/pt/pt_federated_job.py
fl_manager/utils/job_generator/federated_job/pt/pt_federated_job_registry.py
fl_manager/utils/job_generator/federated_job/pt/base/__init__.py
fl_manager/utils/job_generator/federated_job/pt/base/_pt_base_fed_avg_job.py
fl_manager/utils/job_generator/federated_job/pt/base/pt_fed_avg_job.py
fl_manager/utils/job_generator/federated_job/pt/base/pt_fed_bn_job.py
fl_manager/utils/job_generator/federated_job/pt/base/pt_fed_opt_job.py
fl_manager/utils/job_generator/federated_job/pt/base/pt_fed_prox_job.py
fl_manager/utils/job_generator/federated_job/pt/fed_job/__init__.py
fl_manager/utils/job_generator/federated_job/pt/fed_job/base_fed_avg_job.py
fl_manager/utils/job_generator/federated_job/pt/fed_job/base_sag_fed_job.py
fl_manager/utils/job_generator/federated_job/pt/fed_job/fed_avg.py
fl_manager/utils/job_generator/federated_job/pt/fed_job/fed_opt.py
fl_manager/utils/job_generator/schemas/__init__.py
fl_manager/utils/job_generator/schemas/client_config.py
fl_manager/utils/job_generator/schemas/job_config.py
fl_manager_utils_job_generator-0.1.0.dist-info/METADATA
fl_manager_utils_job_generator-0.1.0.dist-info/WHEEL
fl_manager_utils_job_generator-0.1.0.dist-info/licenses/LICENSE
fl_manager_utils_job_generator-0.1.0.dist-info/RECORD
