Metadata-Version: 2.4
Name: fl-manager-utils-job-generator
Version: 0.1.0
Summary: fl-manager nvflare job generator utility
Project-URL: Homepage, https://github.com/public-itg/py-fl-manager
Author-email: Xin Lin <xlin@itg.es>
License: Apache-2.0
License-File: LICENSE
Classifier: Development Status :: 3 - Alpha
Classifier: Intended Audience :: Science/Research
Classifier: License :: OSI Approved :: Apache Software License
Classifier: Operating System :: OS Independent
Classifier: Programming Language :: Python
Classifier: Programming Language :: Python :: 3 :: Only
Classifier: Programming Language :: Python :: 3.10
Classifier: Programming Language :: Python :: 3.11
Classifier: Programming Language :: Python :: 3.12
Classifier: Topic :: Scientific/Engineering
Classifier: Topic :: Scientific/Engineering :: Artificial Intelligence
Classifier: Topic :: Software Development
Classifier: Topic :: Software Development :: Libraries
Classifier: Topic :: Software Development :: Libraries :: Python Modules
Classifier: Typing :: Typed
Requires-Python: >=3.10
Requires-Dist: fl-manager-core==0.*
Requires-Dist: fl-manager-utils-nvflare-extensions==0.*
Requires-Dist: nvflare~=2.5.2
Requires-Dist: pydantic>=2.10.5
Provides-Extra: torch
Requires-Dist: torch>=2.5.1; extra == 'torch'
